cyhdbscan/LICENSE
cyhdbscan/README.MD
cyhdbscan/__init__.py
cyhdbscan/hdbscanner.hpp
cyhdbscan/requirements.txt
cyhdbscan/thirdparty.json
cyhdbscan/uiev.pyx
cyhdbscan/uiev_compile.py
cyhdbscan-0.10.dist-info/LICENSE.rst
cyhdbscan-0.10.dist-info/METADATA
cyhdbscan-0.10.dist-info/WHEEL
cyhdbscan-0.10.dist-info/top_level.txt
cyhdbscan-0.10.dist-info/RECORD
