Metadata-Version: 2.1
Name: cyhdbscan
Version: 0.10
Summary: Very fast hdbscan for Python - written in Cython/C++
Home-page: https://github.com/hansalemaos/cyhdbscan
Author: Johannes Fischer
Author-email: aulasparticularesdealemaosp@gmail.com
License: MIT
Keywords: hdbscan,Cython,cpp
Classifier: Development Status :: 4 - Beta
Classifier: Programming Language :: Python :: 3 :: Only
Classifier: Programming Language :: Python :: 3.10
Classifier: Topic :: Software Development :: Libraries :: Python Modules
Classifier: Topic :: Utilities
License-File: LICENSE.rst
Requires-Dist: Cython
Requires-Dist: setuptools
